Workbook

Sheet Допущения
A1: Допущения и входные данные
A2: Синие ячейки — редактируйте. Чёрные — считаются формулами. Жёлтая заливка — ключевые рычаги.
A4: Параметр | B4: Значение | C4: Ед. | D4: Источник / обоснование
A5: КУРС И ЦЕНЫ
A6: Курс доллара | B6: 86 | C6: ₽/$ | D6: Задан пользователем, 09.09.2026
A7: Цена одной примерки для клиента | B7: 10 | C7: ₽ | D7: Сценарий пользователя
A8: Setup fee (разовый) | B8: 30000 | C8: ₽ | D8: Сценарий пользователя
A9: Текущий тариф (для сравнения) | B9: 8 | C9: ₽ | D9: Действующая тарификация, пакеты 5k/10k/15k
A10: ТАРИФ AI-ГЕНЕРАЦИИ (CometAPI, GPT Image 2.5)
A11: Input-токены | B11: 4 | C11: $/1M | D11: Прайс CometAPI на gpt-image-2.5 (−20% от $5 OpenAI)
A12: Output-токены | B12: 24 | C12: $/1M | D12: Прайс CometAPI (−20% от $30 OpenAI)
A13: Input-токенов на 1 вещь (база) | B13: 3928 | C13: ток. | D13: ЗАМЕР на реальном запросе 09.09.2026
A14: Input-токенов за каждую след. вещь | B14: 1869 | C14: ток. | D14: ЗАМЕР: (9535−3928)/3, 4-слойный образ
A15: Output: токенов на картинку | B15: 1120 | C15: ток. | D15: ДОПУЩЕНИЕ: типовой расход на изображение 1024px
A16: Output: текстовых токенов | B16: 196 | C16: ток. | D16: ЗАМЕР на реальном запросе
A17: КОРЗИНА СЛОЁВ (факт из БД, 2145 примерок)
A18: Доля образов с 1 вещью | B18: 0.796 | C18: % | D18: ФАКТ: 1648+61 нулевых из 2145
A19: Доля образов с 2 вещами | B19: 0.154 | C19: % | D19: ФАКТ: 330 из 2145
A20: Доля образов с 3 вещами | B20: 0.042 | C20: % | D20: ФАКТ: 90 из 2145
A21: Доля образов с 4 вещами | B21: 0.007 | C21: % | D21: ФАКТ: 16 из 2145
A22: ОТКАЗЫ, ВАЛИДАЦИЯ, ХРАНЕНИЕ
A23: Доля лишних оплаченных попыток | B23: 0.195 | C23: % | D23: ФАКТ: (242 ошибки + 130 ретраев) / 1903 доставленных
A24: Доля стоимости неуспешной попытки | B24: 0.36 | C24: % | D24: ДОПУЩЕНИЕ: биллится только input (₽1,52 из ₽4,23)
A25: Стоимость 1 вызова валидации фото | B25: 0.0134 | C25: ₽ | D25: Расчёт: 1700 in + 60 out по $0,08/$0,32 за 1M
A26: Примерок на одно загруженное фото | B26: 3.08 | C26: шт | D26: ФАКТ: 2145 примерок / 697 фото
A27: Надбавка на отклонённые фото | B27: 0.25 | C27: % | D27: ДОПУЩЕНИЕ: +25% вызовов гейткипера впустую
A28: Хранение на 1 примерку | B28: 0.76 | C28: МБ | D28: ЗАМЕР MinIO: результат 384КБ + фото 1,2МБ/3,08
A29: Цена хранения | B29: 4.09 | C29: ₽/ГБ/мес | D29: Hetzner Volume €0,044/ГБ ≈ ₽4,09
A30: Срок хранения (retention) | B30: 3 | C30: мес | D30: ДОПУЩЕНИЕ: 90 дней. ВНИМАНИЕ: сейчас retention НЕ реализован
A31: Запас на бэкапы/репликацию | B31: 3 | C31: x | D31: ДОПУЩЕНИЕ: множитель к чистому объёму
A32: КОММЕРЦИЯ И ПОСТОЯННЫЕ
A33: Комиссия эквайринга | B33: 0.02 | C33: % | D33: ДОПУЩЕНИЕ: 2%. При оплате по счёту = 0%
A34: Стоимость онбординга клиента | B34: 15000 | C34: ₽ | D34: ДОПУЩЕНИЕ: 14 ч × ₽1000/ч + запас
A35: Ставка поддержки | B35: 1000 | C35: ₽/час | D35: ДОПУЩЕНИЕ: полностью нагруженный час
A36: Инфраструктура на клиента в год | B36: 670 | C36: ₽ | D36: CPX41 €40/мес × 15% доли / 10 клиентов
A37: Ставка УСН «Доходы» | B37: 0.06 | C37: % | D37: УСН 6% выгоднее 15%: затраты 54–58% < 60% точки безразличия

Sheet Себестоимость
A1: Себестоимость одной примерки
A3: Вещей в образе | B3: 1 | C3: 2 | D3: 3 | E3: 4 | F3: Взвешенно
A4: Input-токенов | B4: =Допущения!$B$13+(1-1)*Допущения!$B$14 | C4: =Допущения!$B$13+(2-1)*Допущения!$B$14 | D4: =Допущения!$B$13+(3-1)*Допущения!$B$14 | E4: =Допущения!$B$13+(4-1)*Допущения!$B$14
A5: Output-токенов (картинка + текст) | B5: =Допущения!$B$15+Допущения!$B$16 | C5: =Допущения!$B$15+Допущения!$B$16 | D5: =Допущения!$B$15+Допущения!$B$16 | E5: =Допущения!$B$15+Допущения!$B$16
A6: Стоимость генерации, $ | B6: =B4*Допущения!$B$11/1000000+B5*Допущения!$B$12/1000000 | C6: =C4*Допущения!$B$11/1000000+C5*Допущения!$B$12/1000000 | D6: =D4*Допущения!$B$11/1000000+D5*Допущения!$B$12/1000000 | E6: =E4*Допущения!$B$11/1000000+E5*Допущения!$B$12/1000000
A7: Стоимость генерации, ₽ | B7: =B6*Допущения!$B$6 | C7: =C6*Допущения!$B$6 | D7: =D6*Допущения!$B$6 | E7: =E6*Допущения!$B$6 | F7: =SUMPRODUCT(B7:E7,B8:E8)
A8: Доля в реальной корзине | B8: =Допущения!$B$18 | C8: =Допущения!$B$19 | D8: =Допущения!$B$20 | E8: =Допущения!$B$21 | F8: =SUM(B8:E8)
A10: СТАТЬИ СЕБЕСТОИМОСТИ (на 1 доставленную примерку)
A11: Статья | B11: ₽ | C11: Доля | F11: Комментарий
A12: AI-генерация (взвешенная по корзине) | B12: =F7 | C12: =IFERROR(B12/$B$17,0) | F12: Формула: SUMPRODUCT(цена по слоям × доля слоёв)
A13: Отказы и ретраи | B13: =Допущения!$B$23*F7*Допущения!$B$24 | C13: =IFERROR(B13/$B$17,0) | F13: 19,5% лишних попыток × доля стоимости неуспешной
A14: Хранение | B14: =Допущения!$B$28/1024*Допущения!$B$29*Допущения!$B$30*Допущения!$B$31 | C14: =IFERROR(B14/$B$17,0) | F14: МБ→ГБ × цена × срок × запас на бэкапы
A15: Валидация фото (гейткипер) | B15: =Допущения!$B$25*(1+Допущения!$B$27)/Допущения!$B$26 | C15: =IFERROR(B15/$B$17,0) | F15: Стоимость вызова × надбавка / примерок на фото
A16: Трафик / CDN | B16: 0 | C16: =IFERROR(B16/$B$17,0) | F16: Внутри включённых 20 ТБ Hetzner
A17: MARGINAL COST | B17: =SUM(B12:B16) | C17: =IFERROR(B17/$B$17,0)
A18: Эквайринг | B18: =Допущения!$B$33*Допущения!$B$7 | C18: =IFERROR(B18/$B$17,0) | F18: При оплате по счёту = 0 → +4% контрибуции
A19: Marginal с эквайрингом | B19: =B17+B18 | C19: =IFERROR(B19/$B$17,0)
A21: Контрибуция с одной примерки | B21: =Допущения!$B$7-B19
A22: Контрибуционная маржа | B22: =B21/Допущения!$B$7

Sheet P&L по пакетам
A1: P&L по пакетам — цена 10 ₽ + setup fee 30 000 ₽
A2: Горизонт 12 месяцев. ДОПУЩЕНИЕ: пакет полностью использован в течение года.
A4: Статья | B4: Пакет 5 000 | C4: Пакет 15 000 | D4: Пакет 30 000
A5: Объём примерок | B5: 5000 | C5: 15000 | D5: 30000
A6: Setup fee | B6: =Допущения!$B$8 | C6: =Допущения!$B$8 | D6: =Допущения!$B$8
A7: Выручка с примерок | B7: =B5*Допущения!$B$7 | C7: =C5*Допущения!$B$7 | D7: =D5*Допущения!$B$7
A8: ВЫРУЧКА | B8: =B6+B7 | C8: =C6+C7 | D8: =D6+D7
A9: AI + хранение + валидация | B9: =-B5*Себестоимость!$B$17 | C9: =-C5*Себестоимость!$B$17 | D9: =-D5*Себестоимость!$B$17
A10: Эквайринг | B10: =-B8*Допущения!$B$33 | C10: =-C8*Допущения!$B$33 | D10: =-D8*Допущения!$B$33
A11: Онбординг (разовый) | B11: =-Допущения!$B$34 | C11: =-Допущения!$B$34 | D11: =-Допущения!$B$34
A12: Поддержка (12 мес) | B12: =-Допущения!$B$35*IF(B5<=5000,0.5,IF(B5<=15000,1,1.5))*12 | C12: =-Допущения!$B$35*IF(C5<=5000,0.5,IF(C5<=15000,1,1.5))*12 | D12: =-Допущения!$B$35*IF(D5<=5000,0.5,IF(D5<=15000,1,1.5))*12
A13: Инфраструктура | B13: =-Допущения!$B$36*IF(B5>15000,2,1) | C13: =-Допущения!$B$36*IF(C5>15000,2,1) | D13: =-Допущения!$B$36*IF(D5>15000,2,1)
A14: ЗАТРАТЫ | B14: =SUM(B9:B13) | C14: =SUM(C9:C13) | D14: =SUM(D9:D13)
A15: ВАЛОВАЯ ПРИБЫЛЬ | B15: =B8+B14 | C15: =C8+C14 | D15: =D8+D14
A16: Валовая маржа | B16: =B15/B8 | C16: =C15/C8 | D16: =D15/D8
A17: Налог УСН | B17: =-B8*Допущения!$B$37 | C17: =-C8*Допущения!$B$37 | D17: =-D8*Допущения!$B$37
A18: ЧИСТАЯ ПРИБЫЛЬ | B18: =B15+B17 | C18: =C15+C17 | D18: =D15+D17
A19: Чистая маржа | B19: =B18/B8 | C19: =C18/C8 | D19: =D18/D8
A20: Fully-loaded себестоимость / примерка | B20: =-B14/B5 | C20: =-C14/C5 | D20: =-D14/D5
A21: Выручка / примерка | B21: =B8/B5 | C21: =C8/C5 | D21: =D8/D5

Sheet Чувствительность
A1: Чувствительность: что ломает модель
A3: Сценарий | B3: Marginal cost | C3: Контрибуция | D3: Валовая маржа (15k) | E3: Комментарий
A4: База (текущие допущения) | B4: =Себестоимость!B19 | C4: =Допущения!$B$7-B4 | D4: =(15000*Допущения!$B$7+Допущения!$B$8-15000*B4-Допущения!$B$34-Допущения!$B$35*12-Допущения!$B$36)/(15000*Допущения!$B$7+Допущения!$B$8)
A5: Цена AI ×2 | B5: =Себестоимость!B17*2+Себестоимость!B18 | C5: =Допущения!$B$7-B5 | D5: =(15000*Допущения!$B$7+Допущения!$B$8-15000*B5-Допущения!$B$34-Допущения!$B$35*12-Допущения!$B$36)/(15000*Допущения!$B$7+Допущения!$B$8) | E5: Модель ломается: маржа ~7%
A6: Курс 100 ₽/$ | B6: =Себестоимость!B17*(100/Допущения!$B$6)+Себестоимость!B18 | C6: =Допущения!$B$7-B6 | D6: =(15000*Допущения!$B$7+Допущения!$B$8-15000*B6-Допущения!$B$34-Допущения!$B$35*12-Допущения!$B$36)/(15000*Допущения!$B$7+Допущения!$B$8) | E6: Переживаемо: −6 п.п.
A7: Корзина 40/30/20/10% | B7: =Себестоимость!B7*0.4+Себестоимость!C7*0.3+Себестоимость!D7*0.2+Себестоимость!E7*0.1+Себестоимость!B13+Себестоимость!B14+Себестоимость!B15+Себестоимость!B18 | C7: =Допущения!$B$7-B7 | D7: =(15000*Допущения!$B$7+Допущения!$B$8-15000*B7-Допущения!$B$34-Допущения!$B$35*12-Допущения!$B$36)/(15000*Допущения!$B$7+Допущения!$B$8) | E7: Сдвиг в многослойность
A8: Худший (AI×2 + курс 100 + корзина) | B8: =(Себестоимость!B7*0.4+Себестоимость!C7*0.3+Себестоимость!D7*0.2+Себестоимость!E7*0.1)*2*(100/86)+Себестоимость!B13+Себестоимость!B14+Себестоимость!B15+Себестоимость!B18 | C8: =Допущения!$B$7-B8 | D8: =(15000*Допущения!$B$7+Допущения!$B$8-15000*B8-Допущения!$B$34-Допущения!$B$35*12-Допущения!$B$36)/(15000*Допущения!$B$7+Допущения!$B$8) | E8: Каждая примерка убыточна
A10: Ценовой пол при удвоении цены AI (контрибуция = 0): | B10: =B5

Sheet Сравнение тарифов
A1: 10 ₽ + setup 30 000 ₽ против текущих 8 ₽ без setup
A3: Объём примерок | B3: Прибыль: 8 ₽ | C3: Прибыль: 10 ₽ + setup | D3: Разница | E3: Платит клиент: во сколько раз дороже
A4: 1000 | B4: =A4*(Допущения!$B$9-Себестоимость!$B$17-Допущения!$B$9*Допущения!$B$33)-Допущения!$B$34-Допущения!$B$35*12-Допущения!$B$36 | C4: =Допущения!$B$8*(1-Допущения!$B$33)+A4*Себестоимость!$B$21-Допущения!$B$34-Допущения!$B$35*12-Допущения!$B$36 | D4: =C4-B4 | E4: =(Допущения!$B$8+A4*Допущения!$B$7)/(A4*Допущения!$B$9)
A5: 2000 | B5: =A5*(Допущения!$B$9-Себестоимость!$B$17-Допущения!$B$9*Допущения!$B$33)-Допущения!$B$34-Допущения!$B$35*12-Допущения!$B$36 | C5: =Допущения!$B$8*(1-Допущения!$B$33)+A5*Себестоимость!$B$21-Допущения!$B$34-Допущения!$B$35*12-Допущения!$B$36 | D5: =C5-B5 | E5: =(Допущения!$B$8+A5*Допущения!$B$7)/(A5*Допущения!$B$9)
A6: 5000 | B6: =A6*(Допущения!$B$9-Себестоимость!$B$17-Допущения!$B$9*Допущения!$B$33)-Допущения!$B$34-Допущения!$B$35*12-Допущения!$B$36 | C6: =Допущения!$B$8*(1-Допущения!$B$33)+A6*Себестоимость!$B$21-Допущения!$B$34-Допущения!$B$35*12-Допущения!$B$36 | D6: =C6-B6 | E6: =(Допущения!$B$8+A6*Допущения!$B$7)/(A6*Допущения!$B$9)
A7: 10000 | B7: =A7*(Допущения!$B$9-Себестоимость!$B$17-Допущения!$B$9*Допущения!$B$33)-Допущения!$B$34-Допущения!$B$35*12-Допущения!$B$36 | C7: =Допущения!$B$8*(1-Допущения!$B$33)+A7*Себестоимость!$B$21-Допущения!$B$34-Допущения!$B$35*12-Допущения!$B$36 | D7: =C7-B7 | E7: =(Допущения!$B$8+A7*Допущения!$B$7)/(A7*Допущения!$B$9)
A8: 15000 | B8: =A8*(Допущения!$B$9-Себестоимость!$B$17-Допущения!$B$9*Допущения!$B$33)-Допущения!$B$34-Допущения!$B$35*12-Допущения!$B$36 | C8: =Допущения!$B$8*(1-Допущения!$B$33)+A8*Себестоимость!$B$21-Допущения!$B$34-Допущения!$B$35*12-Допущения!$B$36 | D8: =C8-B8 | E8: =(Допущения!$B$8+A8*Допущения!$B$7)/(A8*Допущения!$B$9)
A9: 20000 | B9: =A9*(Допущения!$B$9-Себестоимость!$B$17-Допущения!$B$9*Допущения!$B$33)-Допущения!$B$34-Допущения!$B$35*12-Допущения!$B$36 | C9: =Допущения!$B$8*(1-Допущения!$B$33)+A9*Себестоимость!$B$21-Допущения!$B$34-Допущения!$B$35*12-Допущения!$B$36 | D9: =C9-B9 | E9: =(Допущения!$B$8+A9*Допущения!$B$7)/(A9*Допущения!$B$9)
A10: 30000 | B10: =A10*(Допущения!$B$9-Себестоимость!$B$17-Допущения!$B$9*Допущения!$B$33)-Допущения!$B$34-Допущения!$B$35*12-Допущения!$B$36 | C10: =Допущения!$B$8*(1-Допущения!$B$33)+A10*Себестоимость!$B$21-Допущения!$B$34-Допущения!$B$35*12-Допущения!$B$36 | D10: =C10-B10 | E10: =(Допущения!$B$8+A10*Допущения!$B$7)/(A10*Допущения!$B$9)
A12: Точка безубыточности по клиенту (примерок до окупания подключения)
A13: Сценарий 10 ₽ + setup 30k | B13: =MAX(0,(Допущения!$B$34+Допущения!$B$35*12+Допущения!$B$36-Допущения!$B$8*(1-Допущения!$B$33))/Себестоимость!$B$21)
A14: Сценарий 10 ₽ без setup | B14: =(Допущения!$B$34+Допущения!$B$35*12+Допущения!$B$36)/Себестоимость!$B$21
A15: Текущие 8 ₽ без setup | B15: =(Допущения!$B$34+Допущения!$B$35*12+Допущения!$B$36)/(Допущения!$B$9-Себестоимость!$B$17-Допущения!$B$9*Допущения!$B$33) | D15: Лучший клиент за 5 мес сделал 1 889 примерок

Sheet Риски
A1: Риски: что может сломать модель
A3: # | B3: Риск | C3: Уровень | D3: Что делать
A4: 1 | B4: Токены не пишутся в ai_api_logs — колонки NULL во всех 2 144 строках. Себестоимость в проде физически неизмерима. | C4: КРИТИЧНЫЙ | D4: Включить запись — час работы, до первого договора
A5: 2 | B5: Retention по 152-ФЗ не реализован нигде: ни cron, ни ILM в MinIO. Фото лиц хранятся бессрочно. | C5: КРИТИЧНЫЙ | D5: Юрист + реализация удаления
A6: 3 | B6: Целостность данных: в БД 697 фото и 1 903 примерки, в MinIO — 6 фото и 4 результата. ~99% ссылок битые. | C6: КРИТИЧНЫЙ | D6: Аудит + починка, иначе история примерок пустая
A7: 4 | B7: Вся статистика с одного клиента: 98,9% примерок — MalinaBonita. Корзина слоёв может быть нерепрезентативна. | C7: КРИТИЧНЫЙ | D7: Перепроверить после 2–3 новых клиентов
A8: 5 | B8: Диск 84% (47 ГБ свободно). Один пакет 30k = 22,7 ГБ. | C8: ВЫСОКИЙ | D8: Расширить том до продажи больших пакетов
A9: 6 | B9: Пакеты без срока годности = вечное обязательство. При темпе 378/мес пакет 30k = 6,6 лет. | C9: ВЫСОКИЙ | D9: Срок действия 12 мес + breakage в маржу
A10: 7 | B10: Открытая валютная позиция: выручка в ₽, 93% себестоимости в $. | C10: ВЫСОКИЙ | D10: Индексировать прайс к курсу
A11: 8 | B11: CometAPI — единственная точка отказа, реселлер без SLA + трансграничный платёж. | C11: ВЫСОКИЙ | D11: Держать прямой доступ к провайдеру как запасной
A12: 9 | B12: Порог НДС на УСН снижается поэтапно — съест 5–7 п.п. маржи при росте. | C12: СРЕДНИЙ | D12: Проверить с бухгалтером до фиксации цены
A13: 10 | B13: Секреты (COMETAPI_KEY) в plaintext в env на машине с 8 соседями. | C13: СРЕДНИЙ | D13: Вынести в секрет-хранилище
A14: 11 | B14: Не зафиксировано договором, тарифицируется ли клиенту неудачная примерка (11,3% отказов). | C14: СРЕДНИЙ | D14: Прописать в оферте
A15: 12 | B15: Setup fee делает сделку вдвое дороже для мелкого клиента (2,0× на 5k против 1,38× на 30k). | C15: СРЕДНИЙ | D15: Рассмотреть ступенчатый setup 30k/20k/0
